pyroengine/__init__.py
pyroengine/core.py
pyroengine/version.py
pyroengine/vision.py
pyroengine-0.2.0.dist-info/LICENSE
pyroengine-0.2.0.dist-info/METADATA
pyroengine-0.2.0.dist-info/WHEEL
pyroengine-0.2.0.dist-info/top_level.txt
pyroengine-0.2.0.dist-info/zip-safe
pyroengine-0.2.0.dist-info/RECORD
